ovos_plugin_mplayer/__init__.py
ovos_plugin_mplayer/mplayerlib.py
ovos_plugin_mplayer/version.py
ovos_media_plugin_mplayer-0.1.0a3.dist-info/LICENSE
ovos_media_plugin_mplayer-0.1.0a3.dist-info/METADATA
ovos_media_plugin_mplayer-0.1.0a3.dist-info/WHEEL
ovos_media_plugin_mplayer-0.1.0a3.dist-info/entry_points.txt
ovos_media_plugin_mplayer-0.1.0a3.dist-info/top_level.txt
ovos_media_plugin_mplayer-0.1.0a3.dist-info/RECORD
