Metadata-Version: 2.1
Name: ovos-media-plugin-mplayer
Version: 0.1.0a3
Summary: mplayer plugin for ovos
Home-page: https://github.com/OpenVoiceOS/ovos-media-plugin-mplayer
Author: JarbasAi
Author-email: jarbasai@mailfence.com
License: Apache-2.0
Keywords: ovos audio video OCP plugin
Platform: UNKNOWN
Requires-Dist: ovos-plugin-manager >=0.0.26a5
